{"id":152,"name":"chikorita","stats":{"hp":45,"attack":49,"defense":65,"specialAttack":49,"specialDefense":65,"speed":45},"types":["grass"],"moves":[{"name":"swords-dance","url":"https://pokeapi.co/api/v2/move/14/"},{"name":"cut","url":"https://pokeapi.co/api/v2/move/15/"},{"name":"vine-whip","url":"https://pokeapi.co/api/v2/move/22/"},{"name":"headbutt","url":"https://pokeapi.co/api/v2/move/29/"},{"name":"tackle","url":"https://pokeapi.co/api/v2/move/33/"},{"name":"body-slam","url":"https://pokeapi.co/api/v2/move/34/"},{"name":"double-edge","url":"https://pokeapi.co/api/v2/move/38/"},{"name":"growl","url":"https://pokeapi.co/api/v2/move/45/"},{"name":"counter","url":"https://pokeapi.co/api/v2/move/68/"},{"name":"leech-seed","url":"https://pokeapi.co/api/v2/move/73/"},{"name":"razor-leaf","url":"https://pokeapi.co/api/v2/move/75/"},{"name":"solar-beam","url":"https://pokeapi.co/api/v2/move/76/"},{"name":"poison-powder","url":"https://pokeapi.co/api/v2/move/77/"},{"name":"toxic","url":"https://pokeapi.co/api/v2/move/92/"},{"name":"mimic","url":"https://pokeapi.co/api/v2/move/102/"},{"name":"double-team","url":"https://pokeapi.co/api/v2/move/104/"},{"name":"light-screen","url":"https://pokeapi.co/api/v2/move/113/"},{"name":"reflect","url":"https://pokeapi.co/api/v2/move/115/"},{"name":"flash","url":"https://pokeapi.co/api/v2/move/148/"},{"name":"rest","url":"https://pokeapi.co/api/v2/move/156/"},{"name":"substitute","url":"https://pokeapi.co/api/v2/move/164/"},{"name":"snore","url":"https://pokeapi.co/api/v2/move/173/"},{"name":"curse","url":"https://pokeapi.co/api/v2/move/174/"},{"name":"flail","url":"https://pokeapi.co/api/v2/move/175/"},{"name":"protect","url":"https://pokeapi.co/api/v2/move/182/"},{"name":"mud-slap","url":"https://pokeapi.co/api/v2/move/189/"},{"name":"detect","url":"https://pokeapi.co/api/v2/move/197/"},{"name":"giga-drain","url":"https://pokeapi.co/api/v2/move/202/"},{"name":"endure","url":"https://pokeapi.co/api/v2/move/203/"},{"name":"swagger","url":"https://pokeapi.co/api/v2/move/207/"},{"name":"fury-cutter","url":"https://pokeapi.co/api/v2/move/210/"},{"name":"attract","url":"https://pokeapi.co/api/v2/move/213/"},{"name":"sleep-talk","url":"https://pokeapi.co/api/v2/move/214/"},{"name":"return","url":"https://pokeapi.co/api/v2/move/216/"},{"name":"frustration","url":"https://pokeapi.co/api/v2/move/218/"},{"name":"safeguard","url":"https://pokeapi.co/api/v2/move/219/"},{"name":"sweet-scent","url":"https://pokeapi.co/api/v2/move/230/"},{"name":"iron-tail","url":"https://pokeapi.co/api/v2/move/231/"},{"name":"synthesis","url":"https://pokeapi.co/api/v2/move/235/"},{"name":"hidden-power","url":"https://pokeapi.co/api/v2/move/237/"},{"name":"sunny-day","url":"https://pokeapi.co/api/v2/move/241/"},{"name":"ancient-power","url":"https://pokeapi.co/api/v2/move/246/"},{"name":"facade","url":"https://pokeapi.co/api/v2/move/263/"},{"name":"nature-power","url":"https://pokeapi.co/api/v2/move/267/"},{"name":"ingrain","url":"https://pokeapi.co/api/v2/move/275/"},{"name":"magic-coat","url":"https://pokeapi.co/api/v2/move/277/"},{"name":"refresh","url":"https://pokeapi.co/api/v2/move/287/"},{"name":"secret-power","url":"https://pokeapi.co/api/v2/move/290/"},{"name":"aromatherapy","url":"https://pokeapi.co/api/v2/move/312/"},{"name":"grass-whistle","url":"https://pokeapi.co/api/v2/move/320/"},{"name":"bullet-seed","url":"https://pokeapi.co/api/v2/move/331/"},{"name":"magical-leaf","url":"https://pokeapi.co/api/v2/move/345/"},{"name":"natural-gift","url":"https://pokeapi.co/api/v2/move/363/"},{"name":"wring-out","url":"https://pokeapi.co/api/v2/move/378/"},{"name":"worry-seed","url":"https://pokeapi.co/api/v2/move/388/"},{"name":"seed-bomb","url":"https://pokeapi.co/api/v2/move/402/"},{"name":"energy-ball","url":"https://pokeapi.co/api/v2/move/412/"},{"name":"leaf-storm","url":"https://pokeapi.co/api/v2/move/437/"},{"name":"captivate","url":"https://pokeapi.co/api/v2/move/445/"},{"name":"grass-knot","url":"https://pokeapi.co/api/v2/move/447/"},{"name":"round","url":"https://pokeapi.co/api/v2/move/496/"},{"name":"echoed-voice","url":"https://pokeapi.co/api/v2/move/497/"},{"name":"heal-pulse","url":"https://pokeapi.co/api/v2/move/505/"},{"name":"grass-pledge","url":"https://pokeapi.co/api/v2/move/520/"},{"name":"work-up","url":"https://pokeapi.co/api/v2/move/526/"},{"name":"grassy-terrain","url":"https://pokeapi.co/api/v2/move/580/"},{"name":"confide","url":"https://pokeapi.co/api/v2/move/590/"}],"assets":{"front":{"normal":"https://raw.githubusercontent.com/vinisaveg/pokemon-dataset/main/assets/pokemon/normal-front/gen2/chikorita.gif","shiny":"https://raw.githubusercontent.com/vinisaveg/pokemon-dataset/main/assets/pokemon/shiny-front/gen2/chikorita.gif"},"back":{"normal":"https://raw.githubusercontent.com/vinisaveg/pokemon-dataset/main/assets/pokemon/normal-back/gen2/chikorita.gif","shiny":"https://raw.githubusercontent.com/vinisaveg/pokemon-dataset/main/assets/pokemon/shiny-back/gen2/chikorita.gif"}}}